{"metadata": {"dbt_schema_version": "https://schemas.getdbt.com/dbt/run-results/v1.json", "dbt_version": "0.19.1", "generated_at": "2021-09-21T13:18:37.502306Z", "invocation_id": "eef28a65-4c4d-4287-a091-e23a9ee62b3c", "env": {}}, "results": [{"status": "success", "timing": [{"name": "compile", "started_at": "2021-09-21T13:18:37.321824Z", "completed_at": "2021-09-21T13:18:37.340222Z"}, {"name": "execute", "started_at": "2021-09-21T13:18:37.340415Z", "completed_at": "2021-09-21T13:18:37.340432Z"}], "thread_id": "Thread-1", "execution_time": 0.018824338912963867, "adapter_response": {}, "message": null, "unique_id": "model.atlan_dbt.my_first_dbt_model"}, {"status": "success", "timing": [{"name": "compile", "started_at": "2021-09-21T13:18:37.340824Z", "completed_at": "2021-09-21T13:18:37.355552Z"}, {"name": "execute", "started_at": "2021-09-21T13:18:37.355739Z", "completed_at": "2021-09-21T13:18:37.355749Z"}], "thread_id": "Thread-1", "execution_time": 0.015094280242919922, "adapter_response": {}, "message": null, "unique_id": "model.atlan_dbt.stg_customers"}, {"status": "success", "timing": [{"name": "compile", "started_at": "2021-09-21T13:18:37.356122Z", "completed_at": "2021-09-21T13:18:37.371870Z"}, {"name": "execute", "started_at": "2021-09-21T13:18:37.372088Z", "completed_at": "2021-09-21T13:18:37.372098Z"}], "thread_id": "Thread-1", "execution_time": 0.01615738868713379, "adapter_response": {}, "message": null, "unique_id": "model.atlan_dbt.my_second_dbt_model"}, {"status": "success", "timing": [{"name": "compile", "started_at": "2021-09-21T13:18:37.372461Z", "completed_at": "2021-09-21T13:18:37.393773Z"}, {"name": "execute", "started_at": "2021-09-21T13:18:37.393987Z", "completed_at": "2021-09-21T13:18:37.393999Z"}], "thread_id": "Thread-1", "execution_time": 0.02171158790588379, "adapter_response": {}, "message": null, "unique_id": "test.atlan_dbt.not_null_my_first_dbt_model_id"}, {"status": "success", "timing": [{"name": "compile", "started_at": "2021-09-21T13:18:37.394354Z", "completed_at": "2021-09-21T13:18:37.413855Z"}, {"name": "execute", "started_at": "2021-09-21T13:18:37.414084Z", "completed_at": "2021-09-21T13:18:37.414096Z"}], "thread_id": "Thread-1", "execution_time": 0.019916057586669922, "adapter_response": {}, "message": null, "unique_id": "test.atlan_dbt.unique_my_first_dbt_model_id"}, {"status": "success", "timing": [{"name": "compile", "started_at": "2021-09-21T13:18:37.414464Z", "completed_at": "2021-09-21T13:18:37.430982Z"}, {"name": "execute", "started_at": "2021-09-21T13:18:37.431208Z", "completed_at": "2021-09-21T13:18:37.431221Z"}], "thread_id": "Thread-1", "execution_time": 0.016951322555541992, "adapter_response": {}, "message": null, "unique_id": "model.atlan_dbt.customers"}, {"status": "success", "timing": [{"name": "compile", "started_at": "2021-09-21T13:18:37.431603Z", "completed_at": "2021-09-21T13:18:37.449387Z"}, {"name": "execute", "started_at": "2021-09-21T13:18:37.449566Z", "completed_at": "2021-09-21T13:18:37.449577Z"}], "thread_id": "Thread-1", "execution_time": 0.01814436912536621, "adapter_response": {}, "message": null, "unique_id": "test.atlan_dbt.not_null_my_second_dbt_model_id"}, {"status": "success", "timing": [{"name": "compile", "started_at": "2021-09-21T13:18:37.449946Z", "completed_at": "2021-09-21T13:18:37.466856Z"}, {"name": "execute", "started_at": "2021-09-21T13:18:37.467021Z", "completed_at": "2021-09-21T13:18:37.467031Z"}], "thread_id": "Thread-1", "execution_time": 0.017255544662475586, "adapter_response": {}, "message": null, "unique_id": "test.atlan_dbt.unique_my_second_dbt_model_id"}, {"status": "success", "timing": [{"name": "compile", "started_at": "2021-09-21T13:18:37.467376Z", "completed_at": "2021-09-21T13:18:37.483556Z"}, {"name": "execute", "started_at": "2021-09-21T13:18:37.483738Z", "completed_at": "2021-09-21T13:18:37.483748Z"}], "thread_id": "Thread-1", "execution_time": 0.016537904739379883, "adapter_response": {}, "message": null, "unique_id": "test.atlan_dbt.not_null_customers_customer_id"}, {"status": "success", "timing": [{"name": "compile", "started_at": "2021-09-21T13:18:37.484133Z", "completed_at": "2021-09-21T13:18:37.500785Z"}, {"name": "execute", "started_at": "2021-09-21T13:18:37.500960Z", "completed_at": "2021-09-21T13:18:37.500971Z"}], "thread_id": "Thread-1", "execution_time": 0.017008543014526367, "adapter_response": {}, "message": null, "unique_id": "test.atlan_dbt.unique_customers_customer_id"}], "elapsed_time": 0.36622071266174316, "args": {"log_format": "default", "write_json": true, "partial_parse": true, "profiles_dir": "/usr/src/develop/.dbt", "profile": "user", "use_cache": true, "host": "0.0.0.0", "port": 8580, "version_check": true, "which": "rpc", "compile": true}}